spleendatads
