Metadata-Version: 2.1
Name: spleendatads
Version: 2.0.6
Summary: A ChRIS DS plugin to download a set of spleen data
Home-page: https://github.com/FNNDSC/pl-spleendatads
Author: FNNDSC
Author-email: dev@babyMRI.org
License: MIT
Classifier: License :: OSI Approved :: MIT License
Classifier: Topic :: Scientific/Engineering
Classifier: Topic :: Scientific/Engineering :: Bio-Informatics
Classifier: Topic :: Scientific/Engineering :: Medical Science Apps.
License-File: LICENSE
Requires-Dist: chris_plugin
Provides-Extra: none
Provides-Extra: dev
Requires-Dist: pytest~=7.1; extra == "dev"
